batch_data_test_tool/__init__.py
batch_data_test_tool/status.py
batch_data_test_tool/apps/__init__.py
batch_data_test_tool/apps/coffee.py
batch_data_test_tool/apps/cola.py
batch_data_test_tool/components/__init__.py
batch_data_test_tool/concurrency/multi_threading.py
batch_data_test_tool/tools/__init__.py
batch_data_test_tool/tools/data_processing.py
batch_data_test_tool/tools/get_config.py
batch_data_test_tool/tools/http_request.py
batch_data_test_tool/tools/http_response.py
batch_data_test_tool/tools/structured_log.py
batch_data_test_tool-1.2.0.dist-info/LICENSE
batch_data_test_tool-1.2.0.dist-info/METADATA
batch_data_test_tool-1.2.0.dist-info/WHEEL
batch_data_test_tool-1.2.0.dist-info/entry_points.txt
batch_data_test_tool-1.2.0.dist-info/top_level.txt
batch_data_test_tool-1.2.0.dist-info/RECORD
