Metadata-Version: 2.1
Name: batch-data-test-tool
Version: 1.2.0
Summary: 一个用于批量处理数据并发送HTTP请求的Python工具包
Home-page: https://github.com/zzti-bsj/batch-data-test-tool
Author: zzti-bsj
Author-email: zzti-bsj <otnw_bsj@163.com>
License: MIT
Project-URL: Homepage, https://github.com/zzti-bsj/batch-data-test-tool
Project-URL: Repository, https://github.com/zzti-bsj/batch-data-test-tool
Project-URL: Documentation, https://github.com/zzti-bsj/batch-data-test-tool#readme
Project-URL: Bug Tracker, https://github.com/zzti-bsj/batch-data-test-tool/issues
Keywords: data-processing,http-requests,batch-testing,jupyter,pandas
Classifier: Development Status :: 4 - Beta
Classifier: Intended Audience :: Developers
Classifier: License :: OSI Approved :: MIT License
Classifier: Operating System :: OS Independent
Classifier: Programming Language :: Python :: 3
Classifier: Programming Language :: Python :: 3.8
Classifier: Programming Language :: Python :: 3.9
Classifier: Programming Language :: Python :: 3.10
Classifier: Programming Language :: Python :: 3.11
Classifier: Programming Language :: Python :: 3.12
Classifier: Topic :: Software Development :: Libraries :: Python Modules
Classifier: Topic :: Scientific/Engineering :: Information Analysis
Classifier: Framework :: Jupyter
Requires-Python: >=3.8
License-File: LICENSE
Requires-Dist: pydantic
Requires-Dist: pandas
Requires-Dist: numpy
Requires-Dist: requests
Requires-Dist: json-repair
Requires-Dist: openpyxl
Requires-Dist: ipywidgets
Provides-Extra: dev
Requires-Dist: pytest; extra == "dev"
Requires-Dist: pytest-cov; extra == "dev"
Requires-Dist: black; extra == "dev"
Requires-Dist: flake8; extra == "dev"
Requires-Dist: mypy; extra == "dev"
